tokenlearner_pytorch/__init__.py
tokenlearner_pytorch/tokenlearner_pytorch.py
tokenlearner_pytorch-0.1.2.dist-info/LICENSE
tokenlearner_pytorch-0.1.2.dist-info/METADATA
tokenlearner_pytorch-0.1.2.dist-info/WHEEL
tokenlearner_pytorch-0.1.2.dist-info/top_level.txt
tokenlearner_pytorch-0.1.2.dist-info/RECORD
