Metadata-Version: 2.1
Name: tokenlearner-pytorch
Version: 0.1.2
Summary: Unofficial PyTorch implementation of TokenLearner by Google AI
Home-page: https://github.com/rish-16/tokenlearner-pytorch
Author: Rishabh Anand
Author-email: mail.rishabh.anand@gmail.com
License: MIT
Platform: UNKNOWN
Classifier: Intended Audience :: Science/Research
Classifier: Programming Language :: Python :: 3.6
Requires-Dist: torch
